Metadata-Version: 2.1
Name: GPTConnect
Version: 0.2.4
Summary: A python package to make GPT functions easy
Home-page: https://github.com/SleepyStew/gptconnect
Author: SleepyStew
License: Apache 2.0
License-File: LICENSE
